{"assets/audio/alarm.mp3":["assets/audio/alarm.mp3"],"assets/audio/timer.mp3":["assets/audio/timer.mp3"],"assets/audio/win.mp3":["assets/audio/win.mp3"],"assets/fonts/Roboto-Italic.ttf":["assets/fonts/Roboto-Italic.ttf"],"assets/fonts/Roboto-Regular.ttf":["assets/fonts/Roboto-Regular.ttf"],"assets/images/banana.png":["assets/images/banana.png"],"assets/images/cocoa.png":["assets/images/cocoa.png"],"assets/images/coffee.png":["assets/images/coffee.png"],"assets/images/fair.png":["assets/images/fair.png"],"assets/images/flowers.png":["assets/images/flowers.png"],"assets/images/logo.png":["assets/images/logo.png"],"assets/images/memory.jpg":["assets/images/memory.jpg"],"assets/images/oekologie.png":["assets/images/oekologie.png"],"assets/images/oekologie_done.png":["assets/images/oekologie_done.png"],"assets/images/oekonomie.png":["assets/images/oekonomie.png"],"assets/images/oekonomie_done.png":["assets/images/oekonomie_done.png"],"assets/images/s1_a1.png":["assets/images/s1_a1.png"],"assets/images/s1_a2.png":["assets/images/s1_a2.png"],"assets/images/s1_b1.png":["assets/images/s1_b1.png"],"assets/images/s1_b2.png":["assets/images/s1_b2.png"],"assets/images/s1_c1.png":["assets/images/s1_c1.png"],"assets/images/s1_c2.png":["assets/images/s1_c2.png"],"assets/images/s1_original.png":["assets/images/s1_original.png"],"assets/images/soziales.png":["assets/images/soziales.png"],"assets/images/soziales_done.png":["assets/images/soziales_done.png"],"assets/images/textiles.png":["assets/images/textiles.png"],"assets/images/windraeder.jpg":["assets/images/windraeder.jpg"],"packages/cupertino_icons/assets/CupertinoIcons.ttf":["packages/cupertino_icons/assets/CupertinoIcons.ttf"]}